{"TelegramId":3401251,"Transactions":[{"TransactionTime":"2017-03-21T07:45:50.416+03:00","Products":[{"ProductName":"Жев.драже в сах.глазури Skittles Кисломикс 38г","CategoryName":"Батончики, шоколадные яйца, драже","Price":30.9,"ActualPrice":27.7},{"ProductName":"Напиток Coca-Cola б/алк газ 0.33л ж/б","CategoryName":"Лимонады, газированные напитки","Price":38.4,"ActualPrice":22.96},{"ProductName":"Котлеты Ложкаревъ По-домашнему 500г","CategoryName":"Котлеты, наггетсы, галеты","Price":534.0,"ActualPrice":378.0}]},{"TransactionTime":"2017-06-12T09:15:32.544+03:00","Products":[{"ProductName":"Пельмени Останкинские Традиционные 500г","CategoryName":"Пельмени, вареники, хинкали","Price":333.0,"ActualPrice":256.0},{"ProductName":"Чипсы кукурузные Nachos оригинальные 150г","CategoryName":"Чипсы","Price":79.0,"ActualPrice":33.0}]},{"TransactionTime":"2017-05-26T12:16:12.854+03:00","Products":[{"ProductName":"Наггетсы Мираторг Классические 300г","CategoryName":"Котлеты, наггетсы, галеты","Price":534.0,"ActualPrice":378.0},{"ProductName":"Котлеты Ложкаревъ По-домашнему 500г","CategoryName":"Котлеты, наггетсы, галеты","Price":534.0,"ActualPrice":378.0},{"ProductName":"Напиток Coca-Cola б/алк газ 0.33л ж/б","CategoryName":"Лимонады, газированные напитки","Price":38.4,"ActualPrice":22.96}]},{"TransactionTime":"2017-04-15T05:28:52.427+03:00","Products":[{"ProductName":"Жев.драже в сах.глазури Skittles Кисломикс 38г","CategoryName":"Батончики, шоколадные яйца, драже","Price":30.9,"ActualPrice":27.7},{"ProductName":"Коктейль винный Браво Аморе клубника газ аром 6% 0,5л ж/б","CategoryName":"Слабоалкогольные напитки","Price":303.4,"ActualPrice":296.47},{"ProductName":"Котлеты Ложкаревъ По-домашнему 500г","CategoryName":"Котлеты, наггетсы, галеты","Price":534.0,"ActualPrice":378.0}]},{"TransactionTime":"2017-06-08T12:16:15.255+03:00","Products":[{"ProductName":"Шок.батончик SNICKERS Super 95г","CategoryName":"Батончики, шоколадные яйца, драже","Price":47.4,"ActualPrice":25.09},{"ProductName":"Пельмени Останкинские Традиционные 500г","CategoryName":"Пельмени, вареники, хинкали","Price":333.0,"ActualPrice":256.0}]},{"TransactionTime":"2017-10-21T21:49:28.8075473+03:00","Products":[{"ProductName":"Очиститель воздуха Symphony подснежник 300мл тригер","CategoryName":"Освежители","Price":105.9,"ActualPrice":89.32}]},{"TransactionTime":"2017-10-21T21:49:28.8075473+03:00","Products":[{"ProductName":"Гель д/душа Angry birds Свежесть дня зеленая свинка 200мл","CategoryName":"Средства для ванны и душа","Price":163.4,"ActualPrice":109.66},{"ProductName":"Смесь молочная Similac 2 с 6мес 350г","CategoryName":"Молочные смеси сухие","Price":309.0,"ActualPrice":230.82}]},{"TransactionTime":"2017-08-06T20:38:22.112+03:00","Products":[{"ProductName":"Жев.драже в сах.глазури Skittles Кисломикс 38г","CategoryName":"Батончики, шоколадные яйца, драже","Price":30.9,"ActualPrice":27.7},{"ProductName":"Сухарики пшеничные ХрусTeam XXL Сыр 130г","CategoryName":"Сухарики","Price":60.0,"ActualPrice":20.0}]},{"TransactionTime":"2017-03-15T20:14:25.068+03:00","Products":[{"ProductName":"Коктейль винный Браво Аморе клубника газ аром 6% 0,5л ж/б","CategoryName":"Слабоалкогольные напитки","Price":104.9,"ActualPrice":75.76},{"ProductName":"Чипсы Lay's Сметана/Лук 80г","CategoryName":"Чипсы","Price":79.0,"ActualPrice":33.0},{"ProductName":"Напиток Coca-Cola б/алк газ 0.33л ж/б","CategoryName":"Лимонады, газированные напитки","Price":38.4,"ActualPrice":22.96}]},{"TransactionTime":"2017-10-21T21:49:28.8075473+03:00","Products":[{"ProductName":"Конфеты Самарский кондитер чернослив в шоколаде 240г","CategoryName":"Конфеты","Price":205.9,"ActualPrice":182.61},{"ProductName":"Молоко пастер Веселый Молочник отборное 3,5-4,5% 930мл бут","CategoryName":"Молоко и сливки","Price":68.4,"ActualPrice":60.82}]},{"TransactionTime":"2017-02-24T05:43:57.056+03:00","Products":[{"ProductName":"Наггетсы Мираторг Классические 300г","CategoryName":"Котлеты, наггетсы, галеты","Price":534.0,"ActualPrice":378.0},{"ProductName":"Наггетсы Мираторг Классические 300г","CategoryName":"Котлеты, наггетсы, галеты","Price":534.0,"ActualPrice":378.0}]},{"TransactionTime":"2016-12-12T22:52:33.34+03:00","Products":[{"ProductName":"Пельмени Сибирская коллекция Классические 800г","CategoryName":"Пельмени, вареники, хинкали","Price":333.0,"ActualPrice":256.0},{"ProductName":"Напиток Fanta апельсин б/алк газ 1л пэт","CategoryName":"Лимонады, газированные напитки","Price":84.4,"ActualPrice":48.17}]},{"TransactionTime":"2017-09-28T13:45:03.52+03:00","Products":[{"ProductName":"Наггетсы Мираторг Классические 300г","CategoryName":"Котлеты, наггетсы, галеты","Price":534.0,"ActualPrice":378.0},{"ProductName":"Чипсы кукурузные Nachos оригинальные 150г","CategoryName":"Чипсы","Price":79.0,"ActualPrice":33.0},{"ProductName":"Сидр СОМЕРСБИ 4,7% 0.44л газированный сладкий Балтика","CategoryName":"Слабоалкогольные напитки","Price":54.9,"ActualPrice":30.6},{"ProductName":"Салфетки д/лица Zewa Делюкс Ромашка 60шт","CategoryName":"Салфетки","Price":79.4,"ActualPrice":52.54}]},{"TransactionTime":"2017-10-21T21:49:28.8075473+03:00","Products":[{"ProductName":"Коктейль пастер Чудо молочный клубника 2% 270г","CategoryName":"Молоко и сливки","Price":40.4,"ActualPrice":40.04}]},{"TransactionTime":"2017-10-21T21:49:28.8075473+03:00","Products":[{"ProductName":"Подгузники Happy Junior 12-25кг 1шт","CategoryName":"Подгузники, пеленки, трусики","Price":20.28,"ActualPrice":13.52},{"ProductName":"Масло сливочное Из Вологды 82,5% 180г","CategoryName":"Масло сливочное и маргарин","Price":219.4,"ActualPrice":199.11}]},{"TransactionTime":"2017-05-28T00:36:30.389+03:00","Products":[{"ProductName":"Чипсы кукурузные Nachos оригинальные 150г","CategoryName":"Чипсы","Price":79.0,"ActualPrice":33.0},{"ProductName":"Коктейль винный Браво Аморе клубника газ аром 6% 0,5л ж/б","CategoryName":"Слабоалкогольные напитки","Price":376.4,"ActualPrice":321.39}]},{"TransactionTime":"2017-10-21T21:49:28.8075473+03:00","Products":[{"ProductName":"Шампунь-гель Маша и Медведь 2в1 От макушки до пяточек береза с 3лет 240мл","CategoryName":"Средства для ванны и душа","Price":116.4,"ActualPrice":102.46}]},{"TransactionTime":"2017-07-02T08:54:02.128+03:00","Products":[{"ProductName":"Напиток Fanta апельсин б/алк газ 1л пэт","CategoryName":"Лимонады, газированные напитки","Price":84.4,"ActualPrice":48.17},{"ProductName":"Пельмени Сибирская коллекция Классические 800г","CategoryName":"Пельмени, вареники, хинкали","Price":333.0,"ActualPrice":256.0},{"ProductName":"Напиток Fanta апельсин б/алк газ 1л пэт","CategoryName":"Лимонады, газированные напитки","Price":84.4,"ActualPrice":48.17}]},{"TransactionTime":"2017-04-09T09:02:57.267+03:00","Products":[{"ProductName":"Чипсы кукурузные Nachos оригинальные 150г","CategoryName":"Чипсы","Price":79.0,"ActualPrice":33.0}]},{"TransactionTime":"2016-11-30T18:56:53.222+03:00","Products":[{"ProductName":"Напиток Fanta апельсин б/алк газ 1л пэт","CategoryName":"Лимонады, газированные напитки","Price":84.4,"ActualPrice":48.17}]},{"TransactionTime":"2016-12-30T05:22:43.39+03:00","Products":[{"ProductName":"Наггетсы Мираторг Классические 300г","CategoryName":"Котлеты, наггетсы, галеты","Price":534.0,"ActualPrice":378.0},{"ProductName":"Наггетсы Мираторг Классические 300г","CategoryName":"Котлеты, наггетсы, галеты","Price":534.0,"ActualPrice":378.0},{"ProductName":"Котлеты Ложкаревъ По-домашнему 500г","CategoryName":"Котлеты, наггетсы, галеты","Price":534.0,"ActualPrice":378.0}]},{"TransactionTime":"2016-12-27T21:42:22.304+03:00","Products":[{"ProductName":"Чипсы Lay's Сметана/Лук 80г","CategoryName":"Чипсы","Price":79.0,"ActualPrice":33.0}]},{"TransactionTime":"2017-10-11T06:48:43.104+03:00","Products":[{"ProductName":"Коктейль винный Браво Аморе клубника газ аром 6% 0,5л ж/б","CategoryName":"Слабоалкогольные напитки","Price":376.4,"ActualPrice":321.39},{"ProductName":"Коктейль винный Браво Аморе клубника газ аром 6% 0,5л ж/б","CategoryName":"Слабоалкогольные напитки","Price":104.9,"ActualPrice":75.76},{"ProductName":"Пельмени Останкинские Традиционные 500г","CategoryName":"Пельмени, вареники, хинкали","Price":333.0,"ActualPrice":256.0},{"ProductName":"РОКС З/паста Бионика отбеливающая 74г","CategoryName":"Зубные пасты","Price":247.4,"ActualPrice":194.93}]},{"TransactionTime":"2017-03-19T16:20:19.936+03:00","Products":[{"ProductName":"Жев.драже в сах.глазури Skittles Кисломикс 38г","CategoryName":"Батончики, шоколадные яйца, драже","Price":30.9,"ActualPrice":27.7},{"ProductName":"Коктейль винный Браво Аморе клубника газ аром 6% 0,5л ж/б","CategoryName":"Слабоалкогольные напитки","Price":303.4,"ActualPrice":169.14}]},{"TransactionTime":"2017-09-13T20:34:11.856+03:00","Products":[{"ProductName":"Пельмени Останкинские Традиционные 500г","CategoryName":"Пельмени, вареники, хинкали","Price":333.0,"ActualPrice":256.0},{"ProductName":"Крем-соус Varvello бальзамический с лимоном 250мл","CategoryName":"Уксус, лимонный сок","Price":254.4,"ActualPrice":226.8}]},{"TransactionTime":"2017-08-19T08:54:04.839+03:00","Products":[{"ProductName":"Пельмени Сибирская коллекция Классические 800г","CategoryName":"Пельмени, вареники, хинкали","Price":333.0,"ActualPrice":256.0},{"ProductName":"Коктейль винный Браво Аморе клубника газ аром 6% 0,5л ж/б","CategoryName":"Слабоалкогольные напитки","Price":376.4,"ActualPrice":321.39},{"ProductName":"Напиток Fanta апельсин б/алк газ 1л пэт","CategoryName":"Лимонады, газированные напитки","Price":84.4,"ActualPrice":48.17},{"ProductName":"Презервативы Ромео и Джульетта 3шт","CategoryName":"Контрацептивы, лубриканты, тесты","Price":36.4,"ActualPrice":28.55}]},{"TransactionTime":"2017-09-26T17:21:57.331+03:00","Products":[{"ProductName":"Коктейль винный Браво Аморе клубника газ аром 6% 0,5л ж/б","CategoryName":"Слабоалкогольные напитки","Price":54.9,"ActualPrice":30.6},{"ProductName":"Прокладки ежедневные Bella Perfecta Ultra Green 10+10шт","CategoryName":"Предметы женской гигиены","Price":124.9,"ActualPrice":122.16}]},{"TransactionTime":"2017-01-01T17:38:01.71+03:00","Products":[{"ProductName":"Чипсы Lay's Сметана/Лук 80г","CategoryName":"Чипсы","Price":79.0,"ActualPrice":33.0},{"ProductName":"Напиток Fanta апельсин б/алк газ 1л пэт","CategoryName":"Лимонады, газированные напитки","Price":84.4,"ActualPrice":48.17},{"ProductName":"Чипсы кукурузные Nachos оригинальные 150г","CategoryName":"Чипсы","Price":79.0,"ActualPrice":33.0}]},{"TransactionTime":"2016-12-24T13:15:41.641+03:00","Products":[{"ProductName":"Напиток Fanta апельсин б/алк газ 1л пэт","CategoryName":"Лимонады, газированные напитки","Price":84.4,"ActualPrice":48.17},{"ProductName":"Жев.драже в сах.глазури Skittles Кисломикс 38г","CategoryName":"Батончики, шоколадные яйца, драже","Price":30.9,"ActualPrice":27.7},{"ProductName":"Котлеты Ложкаревъ По-домашнему 500г","CategoryName":"Котлеты, наггетсы, галеты","Price":534.0,"ActualPrice":378.0}]},{"TransactionTime":"2017-05-11T14:02:54.762+03:00","Products":[{"ProductName":"Напиток Coca-Cola б/алк газ 0.33л ж/б","CategoryName":"Лимонады, газированные напитки","Price":38.4,"ActualPrice":22.96},{"ProductName":"Пельмени Сибирская коллекция Классические 800г","CategoryName":"Пельмени, вареники, хинкали","Price":333.0,"ActualPrice":256.0}]},{"TransactionTime":"2017-06-19T19:16:05.161+03:00","Products":[{"ProductName":"Наггетсы Мираторг Классические 300г","CategoryName":"Котлеты, наггетсы, галеты","Price":534.0,"ActualPrice":378.0},{"ProductName":"Котлеты Ложкаревъ По-домашнему 500г","CategoryName":"Котлеты, наггетсы, галеты","Price":534.0,"ActualPrice":378.0}]},{"TransactionTime":"2017-06-24T17:38:10.306+03:00","Products":[{"ProductName":"Наггетсы Мираторг Классические 300г","CategoryName":"Котлеты, наггетсы, галеты","Price":534.0,"ActualPrice":378.0}]},{"TransactionTime":"2017-02-05T16:21:17.968+03:00","Products":[{"ProductName":"Пельмени Останкинские Традиционные 500г","CategoryName":"Пельмени, вареники, хинкали","Price":333.0,"ActualPrice":256.0},{"ProductName":"Напиток Fanta апельсин б/алк газ 1л пэт","CategoryName":"Лимонады, газированные напитки","Price":84.4,"ActualPrice":48.17},{"ProductName":"Напиток Fanta апельсин б/алк газ 1л пэт","CategoryName":"Лимонады, газированные напитки","Price":84.4,"ActualPrice":48.17}]},{"TransactionTime":"2017-04-30T14:48:33.51+03:00","Products":[{"ProductName":"Жев.драже в сах.глазури Skittles Кисломикс 38г","CategoryName":"Батончики, шоколадные яйца, драже","Price":30.9,"ActualPrice":27.7}]},{"TransactionTime":"2017-10-21T21:49:28.8075473+03:00","Products":[{"ProductName":"Печенье овсяное Классическое 300г Полет","CategoryName":"Печенье","Price":69.4,"ActualPrice":61.96},{"ProductName":"Зубная паста детская Splat Juicy вишня 0+","CategoryName":"Гигиена полости рта","Price":96.19,"ActualPrice":83.7},{"ProductName":"Продукт сметанный Альпийская коровка 15% 200г","CategoryName":"Сметана","Price":21.4,"ActualPrice":19.65}]},{"TransactionTime":"2017-02-17T09:15:41.789+03:00","Products":[{"ProductName":"Напиток Fanta апельсин б/алк газ 1л пэт","CategoryName":"Лимонады, газированные напитки","Price":84.4,"ActualPrice":48.17},{"ProductName":"Коктейль винный Браво Аморе клубника газ аром 6% 0,5л ж/б","CategoryName":"Слабоалкогольные напитки","Price":97.0,"ActualPrice":85.96}]},{"TransactionTime":"2017-03-25T06:22:16.054+03:00","Products":[{"ProductName":"Пельмени Останкинские Традиционные 500г","CategoryName":"Пельмени, вареники, хинкали","Price":333.0,"ActualPrice":256.0},{"ProductName":"Коктейль винный Браво Аморе клубника газ аром 6% 0,5л ж/б","CategoryName":"Слабоалкогольные напитки","Price":376.4,"ActualPrice":321.39},{"ProductName":"Пельмени Останкинские Традиционные 500г","CategoryName":"Пельмени, вареники, хинкали","Price":333.0,"ActualPrice":256.0}]},{"TransactionTime":"2017-04-13T10:25:34.876+03:00","Products":[{"ProductName":"Чипсы кукурузные Nachos оригинальные 150г","CategoryName":"Чипсы","Price":79.0,"ActualPrice":33.0}]},{"TransactionTime":"2017-09-21T22:50:05.249+03:00","Products":[{"ProductName":"Шок.батончик SNICKERS Super 95г","CategoryName":"Батончики, шоколадные яйца, драже","Price":47.4,"ActualPrice":25.09},{"ProductName":"Шок.батончик SNICKERS Super 95г","CategoryName":"Батончики, шоколадные яйца, драже","Price":47.4,"ActualPrice":25.09},{"ProductName":"Чипсы Lay's Сметана/Лук 80г","CategoryName":"Чипсы","Price":79.0,"ActualPrice":33.0},{"ProductName":"Приправа Kamis куркума молотая 20г","CategoryName":"Специи, приправы","Price":46.5,"ActualPrice":39.36}]},{"TransactionTime":"2017-10-21T21:49:28.8075473+03:00","Products":[{"ProductName":"Хна Фитокосметик иранская натуральная 125г","CategoryName":"Средства для окрашивания","Price":84.4,"ActualPrice":69.75}]},{"TransactionTime":"2017-01-12T18:48:45.864+03:00","Products":[{"ProductName":"Коктейль винный Браво Аморе клубника газ аром 6% 0,5л ж/б","CategoryName":"Слабоалкогольные напитки","Price":303.4,"ActualPrice":169.14}]},{"TransactionTime":"2017-09-03T14:57:41.338+03:00","Products":[{"ProductName":"Жев.драже в сах.глазури Skittles Кисломикс 38г","CategoryName":"Батончики, шоколадные яйца, драже","Price":30.9,"ActualPrice":27.7},{"ProductName":"Пельмени Останкинские Традиционные 500г","CategoryName":"Пельмени, вареники, хинкали","Price":333.0,"ActualPrice":256.0},{"ProductName":"Бутылочка Нук стекляная 125мл + соска с вентиляцией латекс р1 с рождения","CategoryName":"Товары для малышей","Price":312.4,"ActualPrice":199.38}]},{"TransactionTime":"2017-05-14T10:55:28.415+03:00","Products":[{"ProductName":"Шок.батончик SNICKERS Super 95г","CategoryName":"Батончики, шоколадные яйца, драже","Price":47.4,"ActualPrice":25.09},{"ProductName":"Котлеты Ложкаревъ По-домашнему 500г","CategoryName":"Котлеты, наггетсы, галеты","Price":534.0,"ActualPrice":378.0}]},{"TransactionTime":"2017-04-21T17:54:11.832+03:00","Products":[{"ProductName":"Пельмени Сибирская коллекция Классические 800г","CategoryName":"Пельмени, вареники, хинкали","Price":333.0,"ActualPrice":256.0},{"ProductName":"Чипсы кукурузные Nachos оригинальные 150г","CategoryName":"Чипсы","Price":79.0,"ActualPrice":33.0}]},{"TransactionTime":"2017-02-21T07:16:59.217+03:00","Products":[{"ProductName":"Наггетсы Мираторг Классические 300г","CategoryName":"Котлеты, наггетсы, галеты","Price":534.0,"ActualPrice":378.0}]},{"TransactionTime":"2017-04-18T15:41:50.407+03:00","Products":[{"ProductName":"Чипсы Lay's Сметана/Лук 80г","CategoryName":"Чипсы","Price":79.0,"ActualPrice":33.0},{"ProductName":"Пельмени Сибирская коллекция Классические 800г","CategoryName":"Пельмени, вареники, хинкали","Price":333.0,"ActualPrice":256.0}]},{"TransactionTime":"2017-10-21T21:49:28.8075473+03:00","Products":[{"ProductName":"Лак д/волос Finesse экстрасильной фиксации, 200 мл","CategoryName":"Средства для укладки волос","Price":316.9,"ActualPrice":213.95},{"ProductName":"Масло сладкосливочное Экомилк 82,5% 180г","CategoryName":"Масло сливочное и маргарин","Price":83.9,"ActualPrice":43.58},{"ProductName":"REACH Зубная щетка Floss Clean экстра мягкая","CategoryName":"Зубные щетки","Price":147.4,"ActualPrice":136.54}]},{"TransactionTime":"2017-10-21T21:49:28.8075473+03:00","Products":[{"ProductName":"Чай черный Greenfield Earl grey fantasy 100пак","CategoryName":"Чай черный","Price":209.0,"ActualPrice":148.39},{"ProductName":"Краска д/бровей и ресниц Estel Only looks черн","CategoryName":"Средства для окрашивания","Price":210.9,"ActualPrice":126.2},{"ProductName":"Крем д/лица L'oreal Дермо-Экспертиз Роскошь питания ночной 50мл","CategoryName":"Средства для зрелой кожи","Price":422.9,"ActualPrice":234.72}]},{"TransactionTime":"2017-10-08T13:43:27.703+03:00","Products":[{"ProductName":"Чипсы кукурузные Nachos оригинальные 150г","CategoryName":"Чипсы","Price":79.0,"ActualPrice":33.0},{"ProductName":"Пельмени Сибирская коллекция Классические 800г","CategoryName":"Пельмени, вареники, хинкали","Price":333.0,"ActualPrice":256.0},{"ProductName":"Жев.драже в сах.глазури Skittles Кисломикс 38г","CategoryName":"Батончики, шоколадные яйца, драже","Price":30.9,"ActualPrice":27.7},{"ProductName":"Маринад д/курицы Костровок 300г","CategoryName":"Хрен, горчица, маринад","Price":89.4,"ActualPrice":84.06}]},{"TransactionTime":"2017-10-21T21:49:28.8075473+03:00","Products":[{"ProductName":"Сок Сады Придонья яблоко/вишня с 5мес 200мл т/п","CategoryName":"Напитки для детского питания","Price":20.9,"ActualPrice":18.76}]},{"TransactionTime":"2017-05-07T16:30:26.143+03:00","Products":[{"ProductName":"Сидр СОМЕРСБИ 4,7% 0.44л газированный сладкий Балтика","CategoryName":"Слабоалкогольные напитки","Price":54.9,"ActualPrice":30.6}]},{"TransactionTime":"2017-05-17T20:40:29.331+03:00","Products":[{"ProductName":"Коктейль винный Браво Аморе клубника газ аром 6% 0,5л ж/б","CategoryName":"Слабоалкогольные напитки","Price":97.5,"ActualPrice":76.12}]},{"TransactionTime":"2017-01-20T18:25:55.556+03:00","Products":[{"ProductName":"Жев.драже в сах.глазури Skittles Кисломикс 38г","CategoryName":"Батончики, шоколадные яйца, драже","Price":30.9,"ActualPrice":27.7},{"ProductName":"Чипсы Lay's Сметана/Лук 80г","CategoryName":"Чипсы","Price":79.0,"ActualPrice":33.0}]},{"TransactionTime":"2017-10-21T21:49:28.8075473+03:00","Products":[{"ProductName":"Игрушка Набор Фантазер Голубая глина для лепки","CategoryName":"Развитие и творчество","Price":149.0,"ActualPrice":108.86}]},{"TransactionTime":"2017-10-21T21:49:28.8075473+03:00","Products":[{"ProductName":"Йогурт Danone Даниссимо Фантазия хрустящие шарики 6,9% 105г","CategoryName":"Йогурты и творожки","Price":40.47,"ActualPrice":20.87},{"ProductName":"Кекс творожный ОКЕЙ 400г","CategoryName":"Выпечка, изделия сдобные","Price":105.9,"ActualPrice":88.12},{"ProductName":"Сок Я Премиум грейпфрут розовый с мякотью 0.97л т/п","CategoryName":"Соки, нектары, морсы","Price":74.49,"ActualPrice":59.56}]},{"TransactionTime":"2017-10-16T22:03:53.3+03:00","Products":[{"ProductName":"Напиток Coca-Cola б/алк газ 0.33л ж/б","CategoryName":"Лимонады, газированные напитки","Price":38.4,"ActualPrice":22.96},{"ProductName":"Шок.батончик SNICKERS Super 95г","CategoryName":"Батончики, шоколадные яйца, драже","Price":47.4,"ActualPrice":25.09},{"ProductName":"Коктейль винный Браво Аморе клубника газ аром 6% 0,5л ж/б","CategoryName":"Слабоалкогольные напитки","Price":64.9,"ActualPrice":49.38},{"ProductName":"Сушка Хлебный Дом Малышка простая 400г","CategoryName":"Сухари, баранки, сушки","Price":99.5,"ActualPrice":92.36}]},{"TransactionTime":"2017-03-07T03:19:46.437+03:00","Products":[{"ProductName":"Чипсы кукурузные Nachos оригинальные 150г","CategoryName":"Чипсы","Price":79.0,"ActualPrice":33.0},{"ProductName":"Пельмени Сибирская коллекция Классические 800г","CategoryName":"Пельмени, вареники, хинкали","Price":333.0,"ActualPrice":256.0},{"ProductName":"Шок.батончик SNICKERS Super 95г","CategoryName":"Батончики, шоколадные яйца, драже","Price":47.4,"ActualPrice":25.09}]},{"TransactionTime":"2017-07-24T15:33:52.973+03:00","Products":[{"ProductName":"Пельмени Останкинские Традиционные 500г","CategoryName":"Пельмени, вареники, хинкали","Price":333.0,"ActualPrice":256.0},{"ProductName":"Чипсы кукурузные Nachos оригинальные 150г","CategoryName":"Чипсы","Price":79.0,"ActualPrice":33.0},{"ProductName":"Презервативы Durex Dual Extase рельефные с анестетиком №12","CategoryName":"Контрацептивы, лубриканты, тесты","Price":767.4,"ActualPrice":557.53}]},{"TransactionTime":"2017-07-27T09:52:51.182+03:00","Products":[{"ProductName":"Чипсы кукурузные Nachos оригинальные 150г","CategoryName":"Чипсы","Price":79.0,"ActualPrice":33.0},{"ProductName":"Лосьон д/загара Nivea Мини SPF30 50мл","CategoryName":"Солнцезащитные средства","Price":237.4,"ActualPrice":170.16}]},{"TransactionTime":"2017-03-02T05:11:02.058+03:00","Products":[{"ProductName":"Сидр СОМЕРСБИ 4,7% 0.44л газированный сладкий Балтика","CategoryName":"Слабоалкогольные напитки","Price":54.9,"ActualPrice":30.6},{"ProductName":"Шок.батончик SNICKERS Super 95г","CategoryName":"Батончики, шоколадные яйца, драже","Price":47.4,"ActualPrice":25.09},{"ProductName":"Напиток Fanta апельсин б/алк газ 1л пэт","CategoryName":"Лимонады, газированные напитки","Price":84.4,"ActualPrice":48.17}]},{"TransactionTime":"2017-10-21T21:49:28.8075473+03:00","Products":[{"ProductName":"Пряники Имбирные сердечки 400г Хлебный Дом","CategoryName":"Пряники","Price":91.5,"ActualPrice":82.12}]},{"TransactionTime":"2017-04-04T01:19:58.268+03:00","Products":[{"ProductName":"Жев.драже в сах.глазури Skittles Кисломикс 38г","CategoryName":"Батончики, шоколадные яйца, драже","Price":30.9,"ActualPrice":27.7},{"ProductName":"Пельмени Останкинские Традиционные 500г","CategoryName":"Пельмени, вареники, хинкали","Price":333.0,"ActualPrice":256.0},{"ProductName":"Шок.батончик SNICKERS Super 95г","CategoryName":"Батончики, шоколадные яйца, драже","Price":47.4,"ActualPrice":25.09}]},{"TransactionTime":"2017-02-27T11:11:11.098+03:00","Products":[{"ProductName":"Пельмени Сибирская коллекция Классические 800г","CategoryName":"Пельмени, вареники, хинкали","Price":333.0,"ActualPrice":256.0},{"ProductName":"Котлеты Ложкаревъ По-домашнему 500г","CategoryName":"Котлеты, наггетсы, галеты","Price":534.0,"ActualPrice":378.0},{"ProductName":"Пельмени Сибирская коллекция Классические 800г","CategoryName":"Пельмени, вареники, хинкали","Price":333.0,"ActualPrice":256.0}]},{"TransactionTime":"2017-08-10T03:41:37.244+03:00","Products":[{"ProductName":"Наггетсы Мираторг Классические 300г","CategoryName":"Котлеты, наггетсы, галеты","Price":534.0,"ActualPrice":378.0},{"ProductName":"Чипсы кукурузные Nachos оригинальные 150г","CategoryName":"Чипсы","Price":79.0,"ActualPrice":33.0},{"ProductName":"Коктейль винный Браво Аморе клубника газ аром 6% 0,5л ж/б","CategoryName":"Слабоалкогольные напитки","Price":86.4,"ActualPrice":54.15},{"ProductName":"Презервативы Masculan 1 Ultra №3 нежные с ароматом тутти-фрутти","CategoryName":"Контрацептивы, лубриканты, тесты","Price":128.4,"ActualPrice":66.55}]},{"TransactionTime":"2017-10-21T21:49:28.8075473+03:00","Products":[{"ProductName":"Стиральный порошок жидкий Ласка Актив & Фреш 2л","CategoryName":"Стирка одежды","Price":269.0,"ActualPrice":149.9}]},{"TransactionTime":"2017-01-05T13:32:05.952+03:00","Products":[{"ProductName":"Коктейль винный Браво Аморе клубника газ аром 6% 0,5л ж/б","CategoryName":"Слабоалкогольные напитки","Price":303.4,"ActualPrice":296.47}]},{"TransactionTime":"2017-10-21T21:49:28.8075473+03:00","Products":[{"ProductName":"Каша Nestle молочная мультизлаковая яблоко/банан 220г","CategoryName":"Каши детские","Price":134.0,"ActualPrice":108.63},{"ProductName":"Яйцо куриное С1 Синявинское 10шт","CategoryName":"Яйцо","Price":73.4,"ActualPrice":73.1}]},{"TransactionTime":"2017-10-21T21:49:28.8075473+03:00","Products":[{"ProductName":"Танцевальный коврик","CategoryName":"Развитие и творчество","Price":480.96416708993439,"ActualPrice":-2036.1704347251341},{"ProductName":"Стиральный порошок Ariel Color de Luxe 450г","CategoryName":"Стирка одежды","Price":94.9,"ActualPrice":85.31}]},{"TransactionTime":"2017-02-11T13:29:19.619+03:00","Products":[{"ProductName":"Котлеты Ложкаревъ По-домашнему 500г","CategoryName":"Котлеты, наггетсы, галеты","Price":534.0,"ActualPrice":378.0}]},{"TransactionTime":"2016-12-20T23:53:39.662+03:00","Products":[{"ProductName":"Пельмени Сибирская коллекция Классические 800г","CategoryName":"Пельмени, вареники, хинкали","Price":333.0,"ActualPrice":256.0}]},{"TransactionTime":"2017-10-21T21:49:28.8075473+03:00","Products":[{"ProductName":"Нектар ФрутоНяня яблоко/слива с 5мес 200мл т/п","CategoryName":"Напитки для детского питания","Price":23.49,"ActualPrice":20.49},{"ProductName":"Паста томатная Кубаночка 200г д/п","CategoryName":"Томатные пасты, кетчупы","Price":45.4,"ActualPrice":32.88}]},{"TransactionTime":"2017-10-21T21:49:28.8075473+03:00","Products":[{"ProductName":"Крем д/лица Черный Жемчуг дневной Программа от 36лет 50мл","CategoryName":"Средства для зрелой кожи","Price":195.4,"ActualPrice":141.36},{"ProductName":"Блокиратор дверей Lubby гибкий/большой полиэтилен арт13572/288/12","CategoryName":"Товары для малышей","Price":178.99,"ActualPrice":127.02},{"ProductName":"Смесь панировочная Kamis хрустящая к птице 70г","CategoryName":"Специи, приправы","Price":68.4,"ActualPrice":40.88}]},{"TransactionTime":"2016-12-03T08:00:09.946+03:00","Products":[{"ProductName":"Котлеты Ложкаревъ По-домашнему 500г","CategoryName":"Котлеты, наггетсы, галеты","Price":534.0,"ActualPrice":378.0},{"ProductName":"Коктейль винный Браво Аморе клубника газ аром 6% 0,5л ж/б","CategoryName":"Слабоалкогольные напитки","Price":97.5,"ActualPrice":76.12}]},{"TransactionTime":"2017-03-30T05:11:04.634+03:00","Products":[{"ProductName":"Жев.драже в сах.глазури Skittles Кисломикс 38г","CategoryName":"Батончики, шоколадные яйца, драже","Price":30.9,"ActualPrice":27.7}]},{"TransactionTime":"2017-04-06T07:38:16.458+03:00","Products":[{"ProductName":"Шок.батончик SNICKERS Super 95г","CategoryName":"Батончики, шоколадные яйца, драже","Price":47.4,"ActualPrice":25.09},{"ProductName":"Напиток Coca-Cola б/алк газ 0.33л ж/б","CategoryName":"Лимонады, газированные напитки","Price":38.4,"ActualPrice":22.96},{"ProductName":"Напиток Coca-Cola б/алк газ 0.33л ж/б","CategoryName":"Лимонады, газированные напитки","Price":38.4,"ActualPrice":22.96}]},{"TransactionTime":"2017-10-21T21:49:28.8075473+03:00","Products":[{"ProductName":"Водоросль морская Sen Soy Premium Суши-Нори 10 листов 28г","CategoryName":"Азиатская кухня","Price":131.4,"ActualPrice":65.76}]},{"TransactionTime":"2017-07-05T04:48:02.301+03:00","Products":[{"ProductName":"Коктейль винный Браво Аморе клубника газ аром 6% 0,5л ж/б","CategoryName":"Слабоалкогольные напитки","Price":97.0,"ActualPrice":85.96}]},{"TransactionTime":"2017-06-02T18:00:40.355+03:00","Products":[{"ProductName":"Напиток Coca-Cola б/алк газ 0.33л ж/б","CategoryName":"Лимонады, газированные напитки","Price":38.4,"ActualPrice":22.96},{"ProductName":"Сидр СОМЕРСБИ 4,7% 0.44л газированный сладкий Балтика","CategoryName":"Слабоалкогольные напитки","Price":54.9,"ActualPrice":30.6}]},{"TransactionTime":"2017-09-17T08:36:29.401+03:00","Products":[{"ProductName":"Пельмени Сибирская коллекция Классические 800г","CategoryName":"Пельмени, вареники, хинкали","Price":333.0,"ActualPrice":256.0},{"ProductName":"Коктейль винный Браво Аморе клубника газ аром 6% 0,5л ж/б","CategoryName":"Слабоалкогольные напитки","Price":97.5,"ActualPrice":76.12},{"ProductName":"Пельмени Сибирская коллекция Классические 800г","CategoryName":"Пельмени, вареники, хинкали","Price":333.0,"ActualPrice":256.0},{"ProductName":"Продукт соевый Тофу Росттофу натуральный растительный 500г","CategoryName":"Продукты соевые","Price":151.9,"ActualPrice":117.4}]},{"TransactionTime":"2016-12-15T06:14:14.691+03:00","Products":[{"ProductName":"Коктейль винный Браво Аморе клубника газ аром 6% 0,5л ж/б","CategoryName":"Слабоалкогольные напитки","Price":156.4,"ActualPrice":141.05},{"ProductName":"Котлеты Ложкаревъ По-домашнему 500г","CategoryName":"Котлеты, наггетсы, галеты","Price":534.0,"ActualPrice":378.0}]},{"TransactionTime":"2017-04-26T06:37:31.822+03:00","Products":[{"ProductName":"Шок.батончик SNICKERS Super 95г","CategoryName":"Батончики, шоколадные яйца, драже","Price":47.4,"ActualPrice":25.09},{"ProductName":"Жев.драже в сах.глазури Skittles Кисломикс 38г","CategoryName":"Батончики, шоколадные яйца, драже","Price":30.9,"ActualPrice":27.7}]},{"TransactionTime":"2017-01-23T20:14:48.674+03:00","Products":[{"ProductName":"Жев.драже в сах.глазури Skittles Кисломикс 38г","CategoryName":"Батончики, шоколадные яйца, драже","Price":30.9,"ActualPrice":27.7}]},{"TransactionTime":"2017-03-11T07:40:43.068+03:00","Products":[{"ProductName":"Наггетсы Мираторг Классические 300г","CategoryName":"Котлеты, наггетсы, галеты","Price":534.0,"ActualPrice":378.0},{"ProductName":"Пельмени Останкинские Традиционные 500г","CategoryName":"Пельмени, вареники, хинкали","Price":333.0,"ActualPrice":256.0}]},{"TransactionTime":"2017-03-31T18:13:03.536+03:00","Products":[{"ProductName":"Котлеты Ложкаревъ По-домашнему 500г","CategoryName":"Котлеты, наггетсы, галеты","Price":534.0,"ActualPrice":378.0},{"ProductName":"Жев.драже в сах.глазури Skittles Кисломикс 38г","CategoryName":"Батончики, шоколадные яйца, драже","Price":30.9,"ActualPrice":27.7}]},{"TransactionTime":"2017-10-21T21:49:28.8075473+03:00","Products":[{"ProductName":"BREESAL Освежитель воздуха гел.шарики Энергия фруктов","CategoryName":"Освежители","Price":210.9,"ActualPrice":202.01},{"ProductName":"Игрушка модель машины 1:34-39 в ассортиенте арт42312/43607/43608","CategoryName":"Детские игрушки","Price":499.0,"ActualPrice":445.41},{"ProductName":"Лимонад Shippi New барбарис б/а газ.1.25л ПЭТ","CategoryName":"Лимонады, газированные напитки","Price":52.9,"ActualPrice":37.1}]},{"TransactionTime":"2017-10-21T21:49:28.8075473+03:00","Products":[{"ProductName":"Набор для лепки Genio Kids Пчёлка","CategoryName":"Развитие и творчество","Price":179.0,"ActualPrice":155.88}]},{"TransactionTime":"2017-07-12T02:21:44.492+03:00","Products":[{"ProductName":"Наггетсы Мираторг Классические 300г","CategoryName":"Котлеты, наггетсы, галеты","Price":534.0,"ActualPrice":378.0},{"ProductName":"Наггетсы Мираторг Классические 300г","CategoryName":"Котлеты, наггетсы, галеты","Price":534.0,"ActualPrice":378.0},{"ProductName":"Жев.драже в сах.глазури Skittles Кисломикс 38г","CategoryName":"Батончики, шоколадные яйца, драже","Price":30.9,"ActualPrice":27.7},{"ProductName":"Чипсы кукурузные Nachos оригинальные 150г","CategoryName":"Чипсы","Price":79.0,"ActualPrice":33.0}]},{"TransactionTime":"2017-09-10T03:35:52.593+03:00","Products":[{"ProductName":"Коктейль винный Браво Аморе клубника газ аром 6% 0,5л ж/б","CategoryName":"Слабоалкогольные напитки","Price":97.5,"ActualPrice":76.12},{"ProductName":"Сидр СОМЕРСБИ 4,7% 0.44л газированный сладкий Балтика","CategoryName":"Слабоалкогольные напитки","Price":54.9,"ActualPrice":30.6},{"ProductName":"Пельмени Останкинские Традиционные 500г","CategoryName":"Пельмени, вареники, хинкали","Price":333.0,"ActualPrice":256.0},{"ProductName":"Приправа Kamis гвоздика 10г","CategoryName":"Специи, приправы","Price":64.4,"ActualPrice":35.54}]},{"TransactionTime":"2017-05-03T12:26:54.603+03:00","Products":[{"ProductName":"Шок.батончик SNICKERS Super 95г","CategoryName":"Батончики, шоколадные яйца, драже","Price":47.4,"ActualPrice":25.09},{"ProductName":"Напиток Fanta апельсин б/алк газ 1л пэт","CategoryName":"Лимонады, газированные напитки","Price":84.4,"ActualPrice":48.17},{"ProductName":"Пельмени Сибирская коллекция Классические 800г","CategoryName":"Пельмени, вареники, хинкали","Price":333.0,"ActualPrice":256.0}]},{"TransactionTime":"2017-10-21T21:49:28.8075473+03:00","Products":[{"ProductName":"Cалфетки влажные Aura beauty с антибактериальным эффектом 72шт","CategoryName":"Салфетки","Price":103.4,"ActualPrice":75.3}]},{"TransactionTime":"2017-10-21T21:49:28.8075473+03:00","Products":[{"ProductName":"Корм д/кошек Felix Sensations курица в желе с морковью 85г","CategoryName":"Корм для кошек","Price":25.9,"ActualPrice":13.51},{"ProductName":"Пирожное Orion Choco Pie 360г","CategoryName":"Торты и пирожные","Price":142.4,"ActualPrice":114.17}]},{"TransactionTime":"2016-12-09T22:57:48.402+03:00","Products":[{"ProductName":"Пельмени Останкинские Традиционные 500г","CategoryName":"Пельмени, вареники, хинкали","Price":333.0,"ActualPrice":256.0},{"ProductName":"Чипсы Lay's Сметана/Лук 80г","CategoryName":"Чипсы","Price":79.0,"ActualPrice":33.0}]},{"TransactionTime":"2017-08-16T00:15:40.188+03:00","Products":[{"ProductName":"Напиток Coca-Cola б/алк газ 0.33л ж/б","CategoryName":"Лимонады, газированные напитки","Price":38.4,"ActualPrice":22.96},{"ProductName":"Игрушка д/кошек Triol дразнилка перо","CategoryName":"Аксессуары и средства гигиены для животных","Price":84.9,"ActualPrice":49.7}]},{"TransactionTime":"2016-12-17T20:53:08.252+03:00","Products":[{"ProductName":"Сидр СОМЕРСБИ 4,7% 0.44л газированный сладкий Балтика","CategoryName":"Слабоалкогольные напитки","Price":54.9,"ActualPrice":30.6},{"ProductName":"Коктейль винный Браво Аморе клубника газ аром 6% 0,5л ж/б","CategoryName":"Слабоалкогольные напитки","Price":64.9,"ActualPrice":64.77},{"ProductName":"Пельмени Останкинские Традиционные 500г","CategoryName":"Пельмени, вареники, хинкали","Price":333.0,"ActualPrice":256.0}]},{"TransactionTime":"2017-06-14T22:13:03.186+03:00","Products":[{"ProductName":"Наггетсы Мираторг Классические 300г","CategoryName":"Котлеты, наггетсы, галеты","Price":534.0,"ActualPrice":378.0},{"ProductName":"Чипсы Lay's Сметана/Лук 80г","CategoryName":"Чипсы","Price":79.0,"ActualPrice":33.0},{"ProductName":"Котлеты Ложкаревъ По-домашнему 500г","CategoryName":"Котлеты, наггетсы, галеты","Price":534.0,"ActualPrice":378.0}]},{"TransactionTime":"2017-02-15T03:31:29.556+03:00","Products":[{"ProductName":"Чипсы кукурузные Nachos оригинальные 150г","CategoryName":"Чипсы","Price":79.0,"ActualPrice":33.0},{"ProductName":"Наггетсы Мираторг Классические 300г","CategoryName":"Котлеты, наггетсы, галеты","Price":534.0,"ActualPrice":378.0}]},{"TransactionTime":"2017-10-21T21:49:28.8075473+03:00","Products":[{"ProductName":"Крем д/век Черный Жемчуг Омолаживающий уход Bio-программа 20мл","CategoryName":"Средства для зрелой кожи","Price":130.9,"ActualPrice":109.51},{"ProductName":"Салфетки влажные Aura mix освежающие 20шт","CategoryName":"Салфетки","Price":16.9,"ActualPrice":10.29},{"ProductName":"Вино Эскудо Рохо.Барон Филипп де Ротшильд защищ.наис.кр.сух. 12,5-14% 0,75л (Чили)","CategoryName":"Вино","Price":31.936180386466951,"ActualPrice":-1280.9907123202247}]},{"TransactionTime":"2017-10-01T00:06:34.538+03:00","Products":[{"ProductName":"Котлеты Ложкаревъ По-домашнему 500г","CategoryName":"Котлеты, наггетсы, галеты","Price":534.0,"ActualPrice":378.0},{"ProductName":"Пельмени Останкинские Традиционные 500г","CategoryName":"Пельмени, вареники, хинкали","Price":333.0,"ActualPrice":256.0},{"ProductName":"Соус песто Monini Genovese 190г","CategoryName":"Соусы, заправки","Price":370.9,"ActualPrice":339.61}]},{"TransactionTime":"2017-08-02T21:42:29.726+03:00","Products":[{"ProductName":"Жев.драже в сах.глазури Skittles Кисломикс 38г","CategoryName":"Батончики, шоколадные яйца, драже","Price":30.9,"ActualPrice":27.7},{"ProductName":"Приправа Kamis перец чили 15г","CategoryName":"Специи, приправы","Price":46.5,"ActualPrice":37.78}]},{"TransactionTime":"2017-10-21T21:49:28.8075473+03:00","Products":[{"ProductName":"Торт безе У Палыча Ореховый по-королевски 400г","CategoryName":"Торты и пирожные","Price":581.9,"ActualPrice":406.75},{"ProductName":"Кетчуп Махеевъ шашлычный 500г д/п","CategoryName":"Томатные пасты, кетчупы","Price":63.5,"ActualPrice":59.73}]},{"TransactionTime":"2017-05-10T01:41:51.755+03:00","Products":[{"ProductName":"Жев.драже в сах.глазури Skittles Кисломикс 38г","CategoryName":"Батончики, шоколадные яйца, драже","Price":30.9,"ActualPrice":27.7},{"ProductName":"Котлеты Ложкаревъ По-домашнему 500г","CategoryName":"Котлеты, наггетсы, галеты","Price":534.0,"ActualPrice":378.0}]},{"TransactionTime":"2017-08-25T17:18:59.277+03:00","Products":[{"ProductName":"Напиток Fanta апельсин б/алк газ 1л пэт","CategoryName":"Лимонады, газированные напитки","Price":84.4,"ActualPrice":48.17},{"ProductName":"Котлеты Ложкаревъ По-домашнему 500г","CategoryName":"Котлеты, наггетсы, галеты","Price":534.0,"ActualPrice":378.0},{"ProductName":"Туалетная вода женская Angel My Love 30мл","CategoryName":"Парфюмерия","Price":105.9,"ActualPrice":61.71}]},{"TransactionTime":"2016-12-06T02:34:11.673+03:00","Products":[{"ProductName":"Чипсы Lay's Сметана/Лук 80г","CategoryName":"Чипсы","Price":79.0,"ActualPrice":33.0}]},{"TransactionTime":"2017-07-18T23:11:14.409+03:00","Products":[{"ProductName":"Напиток Fanta апельсин б/алк газ 1л пэт","CategoryName":"Лимонады, газированные напитки","Price":84.4,"ActualPrice":48.17},{"ProductName":"Пельмени Сибирская коллекция Классические 800г","CategoryName":"Пельмени, вареники, хинкали","Price":333.0,"ActualPrice":256.0},{"ProductName":"Коктейль винный Браво Аморе клубника газ аром 6% 0,5л ж/б","CategoryName":"Слабоалкогольные напитки","Price":303.4,"ActualPrice":169.14},{"ProductName":"Пудинг Ehrmann Grand Dessertт со взбитыми сливками двойной орех 4,9% 200г","CategoryName":"Десерты, каши молочные","Price":65.4,"ActualPrice":54.9}]},{"TransactionTime":"2017-01-17T00:13:50.89+03:00","Products":[{"ProductName":"Жев.драже в сах.глазури Skittles Кисломикс 38г","CategoryName":"Батончики, шоколадные яйца, драже","Price":30.9,"ActualPrice":27.7}]},{"TransactionTime":"2017-01-25T20:45:29.435+03:00","Products":[{"ProductName":"Напиток Coca-Cola б/алк газ 0.33л ж/б","CategoryName":"Лимонады, газированные напитки","Price":38.4,"ActualPrice":22.96},{"ProductName":"Напиток Coca-Cola б/алк газ 0.33л ж/б","CategoryName":"Лимонады, газированные напитки","Price":38.4,"ActualPrice":22.96}]},{"TransactionTime":"2017-07-08T14:32:32.577+03:00","Products":[{"ProductName":"Коктейль винный Браво Аморе клубника газ аром 6% 0,5л ж/б","CategoryName":"Слабоалкогольные напитки","Price":54.9,"ActualPrice":30.6},{"ProductName":"Напиток Fanta апельсин б/алк газ 1л пэт","CategoryName":"Лимонады, газированные напитки","Price":84.4,"ActualPrice":48.17},{"ProductName":"Шок.батончик SNICKERS Super 95г","CategoryName":"Батончики, шоколадные яйца, драже","Price":47.4,"ActualPrice":25.09}]},{"TransactionTime":"2017-10-03T22:15:10.651+03:00","Products":[{"ProductName":"Чипсы Lay's Сметана/Лук 80г","CategoryName":"Чипсы","Price":79.0,"ActualPrice":33.0},{"ProductName":"Игрушка Набор машинок Maisto 1:72 на блистере арт15217","CategoryName":"Детские игрушки","Price":449.0,"ActualPrice":400.4}]},{"TransactionTime":"2017-08-31T21:18:44.724+03:00","Products":[{"ProductName":"Пельмени Сибирская коллекция Классические 800г","CategoryName":"Пельмени, вареники, хинкали","Price":333.0,"ActualPrice":256.0},{"ProductName":"Пельмени Сибирская коллекция Классические 800г","CategoryName":"Пельмени, вареники, хинкали","Price":333.0,"ActualPrice":256.0},{"ProductName":"Окорок цыпленка охлажденный","CategoryName":"Мясо и Птица","Price":205.5,"ActualPrice":150.0}]},{"TransactionTime":"2017-01-08T04:25:24.558+03:00","Products":[{"ProductName":"Шок.батончик SNICKERS Super 95г","CategoryName":"Батончики, шоколадные яйца, драже","Price":47.4,"ActualPrice":25.09},{"ProductName":"Пельмени Останкинские Традиционные 500г","CategoryName":"Пельмени, вареники, хинкали","Price":333.0,"ActualPrice":256.0}]},{"TransactionTime":"2017-10-21T21:49:28.8075473+03:00","Products":[{"ProductName":"Лак Wellaflex Объем 2 дня экстрасильная фиксация 250мл","CategoryName":"Средства для укладки волос","Price":237.4,"ActualPrice":119.28},{"ProductName":"Орех лесной Кедровый бор обжаренный 200г","CategoryName":"Орехи, сухофрукты","Price":433.5,"ActualPrice":376.59},{"ProductName":"Набор подарочный Camay French romantique гель д/душа/туалетное мыло романтик 6x(250мл+2x85г)","CategoryName":"Наборы косметические","Price":221.5,"ActualPrice":129.86}]},{"TransactionTime":"2017-08-28T21:59:39.251+03:00","Products":[{"ProductName":"Коктейль винный Браво Аморе клубника газ аром 6% 0,5л ж/б","CategoryName":"Слабоалкогольные напитки","Price":64.9,"ActualPrice":45.06},{"ProductName":"Туалетная бумага Мягкий знак 2сл 6рул","CategoryName":"Туалетная бумага","Price":91.4,"ActualPrice":51.53}]},{"TransactionTime":"2017-05-23T10:00:07.052+03:00","Products":[{"ProductName":"Чипсы кукурузные Nachos оригинальные 150г","CategoryName":"Чипсы","Price":79.0,"ActualPrice":33.0},{"ProductName":"Пельмени Останкинские Традиционные 500г","CategoryName":"Пельмени, вареники, хинкали","Price":333.0,"ActualPrice":256.0},{"ProductName":"Чипсы Lay's Сметана/Лук 80г","CategoryName":"Чипсы","Price":79.0,"ActualPrice":33.0}]},{"TransactionTime":"2017-08-23T03:38:20.529+03:00","Products":[{"ProductName":"Жев.драже в сах.глазури Skittles Кисломикс 38г","CategoryName":"Батончики, шоколадные яйца, драже","Price":30.9,"ActualPrice":27.7},{"ProductName":"Чипсы кукурузные Nachos оригинальные 150г","CategoryName":"Чипсы","Price":79.0,"ActualPrice":33.0},{"ProductName":"Котлеты Ложкаревъ По-домашнему 500г","CategoryName":"Котлеты, наггетсы, галеты","Price":534.0,"ActualPrice":378.0},{"ProductName":"Сосиски Клинский МК Сливочные 470г","CategoryName":"Сосиски, сардельки, колбаски","Price":259.0,"ActualPrice":222.0}]},{"TransactionTime":"2017-07-15T01:38:39.041+03:00","Products":[{"ProductName":"Котлеты Ложкаревъ По-домашнему 500г","CategoryName":"Котлеты, наггетсы, галеты","Price":534.0,"ActualPrice":378.0},{"ProductName":"Напиток Fanta апельсин б/алк газ 1л пэт","CategoryName":"Лимонады, газированные напитки","Price":84.4,"ActualPrice":48.17},{"ProductName":"Коктейль винный Браво Аморе клубника газ аром 6% 0,5л ж/б","CategoryName":"Слабоалкогольные напитки","Price":156.4,"ActualPrice":141.05},{"ProductName":"Нектар Swell черника 0.75л ст/б","CategoryName":"Соки, нектары, морсы","Price":158.9,"ActualPrice":140.33}]},{"TransactionTime":"2017-07-22T05:02:48.687+03:00","Products":[{"ProductName":"Чипсы кукурузные Nachos оригинальные 150г","CategoryName":"Чипсы","Price":79.0,"ActualPrice":33.0},{"ProductName":"Туалетная бумага Мягкий знак 1сл 54м 1рул","CategoryName":"Туалетная бумага","Price":11.4,"ActualPrice":9.03}]},{"TransactionTime":"2017-08-13T03:34:33.665+03:00","Products":[{"ProductName":"Пельмени Останкинские Традиционные 500г","CategoryName":"Пельмени, вареники, хинкали","Price":333.0,"ActualPrice":256.0},{"ProductName":"Чипсы Lay's Сметана/Лук 80г","CategoryName":"Чипсы","Price":79.0,"ActualPrice":33.0},{"ProductName":"Сметана Домик в деревне 25% 330г стакан","CategoryName":"Сметана","Price":84.9,"ActualPrice":52.85}]},{"TransactionTime":"2017-07-29T08:06:22.472+03:00","Products":[{"ProductName":"Чипсы Lay's Сметана/Лук 80г","CategoryName":"Чипсы","Price":79.0,"ActualPrice":33.0},{"ProductName":"Напиток Fanta апельсин б/алк газ 1л пэт","CategoryName":"Лимонады, газированные напитки","Price":84.4,"ActualPrice":48.17},{"ProductName":"Напиток Fanta апельсин б/алк газ 1л пэт","CategoryName":"Лимонады, газированные напитки","Price":84.4,"ActualPrice":48.17},{"ProductName":"Пустышка д/сна Нук Baby Blue с кольцом латекс р1 с рождения","CategoryName":"Товары для малышей","Price":84.0,"ActualPrice":44.33}]},{"TransactionTime":"2017-09-07T08:50:14.309+03:00","Products":[{"ProductName":"Чипсы кукурузные Nachos оригинальные 150г","CategoryName":"Чипсы","Price":79.0,"ActualPrice":33.0},{"ProductName":"Чипсы кукурузные Nachos оригинальные 150г","CategoryName":"Чипсы","Price":79.0,"ActualPrice":33.0},{"ProductName":"Напиток Fanta апельсин б/алк газ 1л пэт","CategoryName":"Лимонады, газированные напитки","Price":84.4,"ActualPrice":48.17},{"ProductName":"Молоко пастеризованное Пискаревское 2,5% 0,5л тфа","CategoryName":"Молоко и сливки","Price":33.4,"ActualPrice":27.13}]},{"TransactionTime":"2017-04-28T08:33:29.245+03:00","Products":[{"ProductName":"Наггетсы Мираторг Классические 300г","CategoryName":"Котлеты, наггетсы, галеты","Price":534.0,"ActualPrice":378.0},{"ProductName":"Напиток Coca-Cola б/алк газ 0.33л ж/б","CategoryName":"Лимонады, газированные напитки","Price":38.4,"ActualPrice":22.96}]},{"TransactionTime":"2017-10-21T21:49:28.8075473+03:00","Products":[{"ProductName":"Майонез Ряба Провансаль сметанный 67% 372г д/п","CategoryName":"Майонез","Price":69.4,"ActualPrice":40.54}]},{"TransactionTime":"2017-10-21T21:49:28.8075473+03:00","Products":[{"ProductName":"Чай зеленый ОКЕЙ с жасмином 25пак","CategoryName":"Чай зеленый","Price":52.99,"ActualPrice":35.44},{"ProductName":"Пятновыводитель Ушастый Нянь 500г","CategoryName":"Средства по уходу за тканями","Price":126.4,"ActualPrice":106.41}]},{"TransactionTime":"2016-11-27T08:28:48.624+03:00","Products":[{"ProductName":"Напиток Coca-Cola б/алк газ 0.33л ж/б","CategoryName":"Лимонады, газированные напитки","Price":38.4,"ActualPrice":22.96}]},{"TransactionTime":"2017-10-21T21:49:28.8075473+03:00","Products":[{"ProductName":"Oral-B Зубная щетка Advantage 3DWhite 40 сред.","CategoryName":"Зубные щетки","Price":157.9,"ActualPrice":157.57}]},{"TransactionTime":"2017-06-26T20:23:31.951+03:00","Products":[{"ProductName":"Шок.батончик SNICKERS Super 95г","CategoryName":"Батончики, шоколадные яйца, драже","Price":47.4,"ActualPrice":25.09},{"ProductName":"Сидр СОМЕРСБИ 4,7% 0.44л газированный сладкий Балтика","CategoryName":"Слабоалкогольные напитки","Price":54.9,"ActualPrice":30.6},{"ProductName":"Пельмени Останкинские Традиционные 500г","CategoryName":"Пельмени, вареники, хинкали","Price":333.0,"ActualPrice":256.0}]},{"TransactionTime":"2017-02-02T17:18:32.007+03:00","Products":[{"ProductName":"Напиток Fanta апельсин б/алк газ 1л пэт","CategoryName":"Лимонады, газированные напитки","Price":84.4,"ActualPrice":48.17}]},{"TransactionTime":"2017-01-30T05:06:41.614+03:00","Products":[{"ProductName":"Шок.батончик SNICKERS Super 95г","CategoryName":"Батончики, шоколадные яйца, драже","Price":47.4,"ActualPrice":25.09},{"ProductName":"Жев.драже в сах.глазури Skittles Кисломикс 38г","CategoryName":"Батончики, шоколадные яйца, драже","Price":30.9,"ActualPrice":27.7},{"ProductName":"Пельмени Сибирская коллекция Классические 800г","CategoryName":"Пельмени, вареники, хинкали","Price":333.0,"ActualPrice":256.0}]},{"TransactionTime":"2017-06-06T12:36:44.885+03:00","Products":[{"ProductName":"Напиток Fanta апельсин б/алк газ 1л пэт","CategoryName":"Лимонады, газированные напитки","Price":84.4,"ActualPrice":48.17},{"ProductName":"Котлеты Ложкаревъ По-домашнему 500г","CategoryName":"Котлеты, наггетсы, галеты","Price":534.0,"ActualPrice":378.0},{"ProductName":"Напиток Coca-Cola б/алк газ 0.33л ж/б","CategoryName":"Лимонады, газированные напитки","Price":38.4,"ActualPrice":22.96}]},{"TransactionTime":"2017-03-13T15:36:30.787+03:00","Products":[{"ProductName":"Шок.батончик SNICKERS Super 95г","CategoryName":"Батончики, шоколадные яйца, драже","Price":47.4,"ActualPrice":25.09}]},{"TransactionTime":"2017-06-29T16:23:14.767+03:00","Products":[{"ProductName":"Чипсы Lay's Сметана/Лук 80г","CategoryName":"Чипсы","Price":79.0,"ActualPrice":33.0}]}]}